em_app/__init__.py
em_app/plotting.py
em_app/solvers.py
em_app/sources.py
em_app/vector_fields.py
em_app-0.2.7.dist-info/licenses/LICENSE
em_app-0.2.7.dist-info/METADATA
em_app-0.2.7.dist-info/WHEEL
em_app-0.2.7.dist-info/top_level.txt
em_app-0.2.7.dist-info/RECORD
