Metadata-Version: 2.4
Name: em-app
Version: 0.2.7
Summary: A package for Electromagnetic applications using MTFLibrary.
Author-email: Shashikant Manikonda <manikonda@outlook.com>
License: MIT License
Project-URL: Homepage, https://github.com/shashi-manikonda/em-simulation-platform
Project-URL: Bug Tracker, https://github.com/shashi-manikonda/em-simulation-platform/issues
Classifier: Development Status :: 4 - Beta
Classifier: Intended Audience :: Developers
Classifier: Intended Audience :: Science/Research
Classifier: License :: OSI Approved :: MIT License
Classifier: Programming Language :: Python :: 3
Classifier: Topic :: Scientific/Engineering :: Mathematics
Classifier: Topic :: Software Development :: Libraries
Requires-Python: >=3.9
License-File: LICENSE
Requires-Dist: numpy
Requires-Dist: mtflib==1.5.2
Requires-Dist: matplotlib
Requires-Dist: pandas
Provides-Extra: dev
Requires-Dist: pytest; extra == "dev"
Requires-Dist: jupytext; extra == "dev"
Requires-Dist: nbconvert; extra == "dev"
Requires-Dist: ipykernel; extra == "dev"
Requires-Dist: pandas-stubs; extra == "dev"
Provides-Extra: benchmark
Requires-Dist: matplotlib; extra == "benchmark"
Requires-Dist: mpi4py; extra == "benchmark"
Provides-Extra: docs
Requires-Dist: sphinx; extra == "docs"
Requires-Dist: sphinx_rtd_theme; extra == "docs"
Dynamic: license-file
